bthci/__init__.py
bthci/acl_data_pkt.py
bthci/bluez_hci.py
bthci/commands.py
bthci/controller_error_codes.py
bthci/events.py
bthci/exception.py
bthci/h4.py
bthci/hci.py
bthci/opcode_group_fields.py
bthci/pytransform/__init__.py
bthci/pytransform/platforms/linux/aarch64/_pytransform.so
bthci/pytransform/platforms/linux/x86_64/_pytransform.so
bthci-0.0.44.dist-info/LICENSE.txt
bthci-0.0.44.dist-info/METADATA
bthci-0.0.44.dist-info/WHEEL
bthci-0.0.44.dist-info/top_level.txt
bthci-0.0.44.dist-info/RECORD
