Metadata-Version: 2.1
Name: bthci
Version: 0.0.44
Summary: Bluetooth HCI Utilities
Home-page: https://pypi.org/project/bthci
Author: Cibo
Author-email: cibo@bio-electric.com
License: Proprietary
Classifier: Operating System :: POSIX :: Linux
Classifier: Programming Language :: Python :: 3
Classifier: Programming Language :: Python :: 3 :: Only
Classifier: Programming Language :: Python :: 3.10
Classifier: License :: Other/Proprietary License
Requires-Python: ==3.10.*
License-File: LICENSE.txt
Requires-Dist: dbus-python (>=1.3.2)
Requires-Dist: xpycommon (>=0.0.25)
